tests/__init__.py
tests/test_always_open.py
tests/test_calendar_dispatcher.py
tests/test_cmes_calendar.py
tests/test_iepa_calendar.py
tests/test_trading_calendar.py
tests/test_weekday_calendar.py
tests/test_xams_calendar.py
tests/test_xbru_calendar.py
tests/test_xcbf_calendar.py
tests/test_xfra_calendar.py
tests/test_xlis_calendar.py
tests/test_xlon_calendar.py
tests/test_xnys_calendar.py
tests/test_xpar_calendar.py
tests/test_xswx_calendar.py
tests/test_xtks_calendar.py
tests/test_xtse_calendar.py
trading_calendars/__init__.py
trading_calendars/_version.py
trading_calendars/always_open.py
trading_calendars/calendar_helpers.py
trading_calendars/calendar_utils.py
trading_calendars/common_holidays.py
trading_calendars/errors.py
trading_calendars/exchange_calendar_bvmf.py
trading_calendars/exchange_calendar_cmes.py
trading_calendars/exchange_calendar_iepa.py
trading_calendars/exchange_calendar_xams.py
trading_calendars/exchange_calendar_xbru.py
trading_calendars/exchange_calendar_xcbf.py
trading_calendars/exchange_calendar_xfra.py
trading_calendars/exchange_calendar_xlis.py
trading_calendars/exchange_calendar_xlon.py
trading_calendars/exchange_calendar_xnys.py
trading_calendars/exchange_calendar_xpar.py
trading_calendars/exchange_calendar_xswx.py
trading_calendars/exchange_calendar_xtks.py
trading_calendars/exchange_calendar_xtse.py
trading_calendars/trading_calendar.py
trading_calendars/us_futures_calendar.py
trading_calendars/us_holidays.py
trading_calendars/weekday_calendar.py
trading_calendars/xtks_holidays.py
trading_calendars/utils/__init__.py
trading_calendars/utils/compat.py
trading_calendars/utils/memoize.py
trading_calendars/utils/pandas_utils.py
trading_calendars/utils/preprocess.py
trading_calendars-1.2.0.dist-info/LICENSE.txt
trading_calendars-1.2.0.dist-info/METADATA
trading_calendars-1.2.0.dist-info/RECORD
trading_calendars-1.2.0.dist-info/WHEEL
trading_calendars-1.2.0.dist-info/top_level.txt
